lyncs_mpi
