Metadata-Version: 2.1
Name: lyncs-mpi
Version: 0.1.3
Summary: Utils for interfacing to MPI libraries using mpi4py and dask
Home-page: https://github.com/Lyncs-API/lyncs.mpi
Author: Simone Bacchio
Author-email: s.bacchio@gmail.com
License: UNKNOWN
Project-URL: Source, https://github.com/Lyncs-API/lyncs.mpi
Project-URL: Documentation, https://github.com/Lyncs-API/lyncs.mpi/README.md
Project-URL: Tracker, https://github.com/Lyncs-API/lyncs.mpi/issues
Project-URL: Download, https://github.com/Lyncs-API/lyncs.mpi/archive/master.zip
Keywords: Utils,interfacing,using,mpi4py,MPI,libraries
Platform: UNKNOWN
Classifier: Development Status :: 2 - Pre-Alpha
Classifier: Intended Audience :: Developers
Classifier: Intended Audience :: Education
Classifier: Intended Audience :: Science/Research
Classifier: License :: OSI Approved :: BSD License
Classifier: Natural Language :: English
Classifier: Operating System :: Unix
Classifier: Programming Language :: C
Classifier: Programming Language :: C++
Classifier: Programming Language :: Python :: 3 :: Only
Classifier: Topic :: Scientific/Engineering :: Physics
Provides-Extra: test
Provides-Extra: all
